matjipyojeong/__init__.py
matjipyojeong/data_loader.py
matjipyojeong/exclude.py
matjipyojeong/recommender.py
matjipyojeong/synonyms.py
matjipyojeong-0.1.1.dist-info/licenses/LICENSE.txt
matjipyojeong-0.1.1.dist-info/METADATA
matjipyojeong-0.1.1.dist-info/WHEEL
matjipyojeong-0.1.1.dist-info/top_level.txt
matjipyojeong-0.1.1.dist-info/RECORD
