Metadata-Version: 2.4
Name: matjipyojeong
Version: 0.1.1
Summary: 지역 기반 식당 검색을 위한 파이썬 라이브러리
Author: Bonitabueno
Author-email: Bonitabueno <admin@0331project.dooray.com>
License: MIT
Project-URL: Homepage, https://0331project.tistory.com/
Requires-Python: >=3.8
License-File: LICENSE.txt
Requires-Dist: pandas
Dynamic: author
Dynamic: license-file
Dynamic: requires-python
